autocomplete_yichunshi/__init__.py
autocomplete_yichunshi-0.1.dist-info/METADATA
autocomplete_yichunshi-0.1.dist-info/WHEEL
autocomplete_yichunshi-0.1.dist-info/top_level.txt
autocomplete_yichunshi-0.1.dist-info/RECORD
