Metadata-Version: 2.1
Name: autocomplete-yichunshi
Version: 0.1
Summary: freakin awesome autocomplete system
Home-page: https://github.com/aliceshiyichun/autocomplete_yichunshi
Author: Yichun Shi
Author-email: yichunsh@andrew.cmu.edu
License: CMU
Platform: UNKNOWN
